fastapi_core_auth/__init__.py
fastapi_core_auth/repository.py
fastapi_core_auth/router.py
fastapi_core_auth/schemas.py
rodrigo0000_fastapi_core_auth-1.0.0.dist-info/METADATA
rodrigo0000_fastapi_core_auth-1.0.0.dist-info/WHEEL
rodrigo0000_fastapi_core_auth-1.0.0.dist-info/top_level.txt
rodrigo0000_fastapi_core_auth-1.0.0.dist-info/RECORD
